draftfast/__init__.py
draftfast/command_line.py
draftfast/dke_exceptions.py
draftfast/exposure.py
draftfast/lineup_constraints.py
draftfast/optimize.py
draftfast/optimizer.py
draftfast/orm.py
draftfast/player_pool.py
draftfast/rules.py
draftfast/settings.py
draftfast/csv_parse/__init__.py
draftfast/csv_parse/mlb_upload.py
draftfast/csv_parse/nba_upload.py
draftfast/csv_parse/nfl_upload.py
draftfast/csv_parse/salary_download.py
draftfast/csv_parse/uploaders.py
draftfast/nba/__init__.py
draftfast/nba/data_cleaning_constants.py
draftfast/nfl/__init__.py
draftfast/nfl/data_cleaning_constants.py
draftfast/nfl/ppr.py
draftfast/nfl/prepare_data.py
draftfast/pickem/__init__.py
draftfast/pickem/pickem_command_line.py
draftfast/pickem/pickem_optimize.py
draftfast/pickem/pickem_orm.py
draftfast/pickem/pickem_upload.py
draftfast/showdown/__init__.py
draftfast/showdown/orm.py
draftfast/test/__init__.py
draftfast/test/test_command_line.py
draftfast/test/test_csv_parse.py
draftfast/test/test_csv_upload.py
draftfast/test/test_custom.py
draftfast/test/test_el.py
draftfast/test/test_exposure.py
draftfast/test/test_lineup_constraints.py
draftfast/test/test_nba_general.py
draftfast/test/test_nfl_showdown.py
draftfast/test/test_nhl.py
draftfast/test/test_optimize.py
draftfast/test/test_pickem.py
draftfast/test/test_player.py
draftfast/test/test_player_pool.py
draftfast/test/test_roster.py
draftfast/test/test_soccer.py
examples/__init__.py
examples/nba.py
examples/pickem.py
examples/showdown.py
tfb_draftfast-1.0.0.dist-info/METADATA
tfb_draftfast-1.0.0.dist-info/WHEEL
tfb_draftfast-1.0.0.dist-info/top_level.txt
tfb_draftfast-1.0.0.dist-info/RECORD
