Metadata-Version: 2.1
Name: tfb-draftfast
Version: 1.0.0
Summary: A tool to automate and optimize DraftKings and FanDuel lineup construction.
Home-page: https://github.com/drew-tfb/tfb-draftfast
Author: Drew
Author-email: drew@thefantasybros.com
License: UNKNOWN
Platform: UNKNOWN
Classifier: Programming Language :: Python :: 3
Classifier: License :: OSI Approved :: MIT License
Classifier: Operating System :: OS Independent
Requires-Dist: numpy (==1.15.4)
Requires-Dist: terminaltables (==3.1.0)
Requires-Dist: ortools (==7.3.7083)
